{"TimestampUtc":"2025-12-19T11:27:39.2847052Z","ReferenceSignalDb":"NaN","Sweep":[{"ControlName":"Headphones","ChannelName":"Both","Value":-4096,"SignalRms":"NaN","NoiseRms":"NaN","SNRdB":"NaN"},{"ControlName":"Headphones","ChannelName":"Both","Value":0,"SignalRms":"NaN","NoiseRms":"NaN","SNRdB":"NaN"},{"ControlName":"Headphones","ChannelName":"Both","Value":4096,"SignalRms":"NaN","NoiseRms":"NaN","SNRdB":"NaN"},{"ControlName":"Aux","ChannelName":"Both","Value":-4096,"SignalRms":"NaN","NoiseRms":"NaN","SNRdB":"NaN"},{"ControlName":"Aux","ChannelName":"Both","Value":0,"SignalRms":"NaN","NoiseRms":"NaN","SNRdB":"NaN"},{"ControlName":"Aux","ChannelName":"Both","Value":4096,"SignalRms":"NaN","NoiseRms":"NaN","SNRdB":"NaN"},{"ControlName":"ADC","ChannelName":"Both","Value":-4096,"SignalRms":"NaN","NoiseRms":"NaN","SNRdB":"NaN"},{"ControlName":"ADC","ChannelName":"Both","Value":0,"SignalRms":"NaN","NoiseRms":"NaN","SNRdB":"NaN"},{"ControlName":"ADC","ChannelName":"Both","Value":4096,"SignalRms":"NaN","NoiseRms":"NaN","SNRdB":"NaN"},{"ControlName":"DAC","ChannelName":"Both","Value":-4096,"SignalRms":"NaN","NoiseRms":"NaN","SNRdB":"NaN"},{"ControlName":"DAC","ChannelName":"Both","Value":0,"SignalRms":"NaN","NoiseRms":"NaN","SNRdB":"NaN"},{"ControlName":"DAC","ChannelName":"Both","Value":4096,"SignalRms":"NaN","NoiseRms":"NaN","SNRdB":"NaN"},{"ControlName":"MixIn PG","ChannelName":"Both","Value":-4096,"SignalRms":"NaN","NoiseRms":"NaN","SNRdB":"NaN"},{"ControlName":"MixIn PG","ChannelName":"Both","Value":0,"SignalRms":"NaN","NoiseRms":"NaN","SNRdB":"NaN"},{"ControlName":"MixIn PG","ChannelName":"Both","Value":4096,"SignalRms":"NaN","NoiseRms":"NaN","SNRdB":"NaN"},{"ControlName":"DAC EQ 1","ChannelName":"Both","Value":-4096,"SignalRms":"NaN","NoiseRms":"NaN","SNRdB":"NaN"},{"ControlName":"DAC EQ 1","ChannelName":"Both","Value":0,"SignalRms":"NaN","NoiseRms":"NaN","SNRdB":"NaN"},{"ControlName":"DAC EQ 1","ChannelName":"Both","Value":4096,"SignalRms":"NaN","NoiseRms":"NaN","SNRdB":"NaN"},{"ControlName":"DAC EQ 2","ChannelName":"Both","Value":-4096,"SignalRms":"NaN","NoiseRms":"NaN","SNRdB":"NaN"},{"ControlName":"DAC EQ 2","ChannelName":"Both","Value":0,"SignalRms":"NaN","NoiseRms":"NaN","SNRdB":"NaN"},{"ControlName":"DAC EQ 2","ChannelName":"Both","Value":4096,"SignalRms":"NaN","NoiseRms":"NaN","SNRdB":"NaN"},{"ControlName":"DAC EQ 3","ChannelName":"Both","Value":-4096,"SignalRms":"NaN","NoiseRms":"NaN","SNRdB":"NaN"},{"ControlName":"DAC EQ 3","ChannelName":"Both","Value":0,"SignalRms":"NaN","NoiseRms":"NaN","SNRdB":"NaN"},{"ControlName":"DAC EQ 3","ChannelName":"Both","Value":4096,"SignalRms":"NaN","NoiseRms":"NaN","SNRdB":"NaN"},{"ControlName":"DAC EQ 4","ChannelName":"Both","Value":-4096,"SignalRms":"NaN","NoiseRms":"NaN","SNRdB":"NaN"},{"ControlName":"DAC EQ 4","ChannelName":"Both","Value":0,"SignalRms":"NaN","NoiseRms":"NaN","SNRdB":"NaN"},{"ControlName":"DAC EQ 4","ChannelName":"Both","Value":4096,"SignalRms":"NaN","NoiseRms":"NaN","SNRdB":"NaN"},{"ControlName":"DAC EQ 5","ChannelName":"Both","Value":-4096,"SignalRms":"NaN","NoiseRms":"NaN","SNRdB":"NaN"},{"ControlName":"DAC EQ 5","ChannelName":"Both","Value":0,"SignalRms":"NaN","NoiseRms":"NaN","SNRdB":"NaN"},{"ControlName":"DAC EQ 5","ChannelName":"Both","Value":4096,"SignalRms":"NaN","NoiseRms":"NaN","SNRdB":"NaN"}]}
